pyplaces/__about__.py
pyplaces/__init__.py
pyplaces/_category_finder.py
pyplaces/_geo_utils.py
pyplaces/_io_utils.py
pyplaces/_utils.py
pyplaces/foursquare_open_places.py
pyplaces/overture_maps.py
pyplaces/releases/foursquare/releases.txt
pyplaces/releases/overture/base_types.txt
pyplaces/releases/overture/releases.txt
pyplaces-0.4.5.dist-info/METADATA
pyplaces-0.4.5.dist-info/WHEEL
pyplaces-0.4.5.dist-info/licenses/LICENSE.txt
pyplaces-0.4.5.dist-info/RECORD
