Metadata-Version: 2.4
Name: pyplaces
Version: 0.4.5
Summary: pyplaces is a Python package meant to streamline the usage of large places datasets, notably Overture Maps and Foursquare Open Places. All of the datasets and past releases can be downloaded to a specific address, place or bounding box. Conventionally, users download the data themselves or use a tool such as DuckDB to download what they need, whereas pyplaces is more integrated, faster, and more precise.
Project-URL: Documentation, https://github.com/unknown/pyplaces#readme
Project-URL: Issues, https://github.com/unknown/pyplaces/issues
Project-URL: Source, https://github.com/tbanken/pyplaces
Author-email: Ted Banken <tedbanken@gmail.com>
License-Expression: MIT
License-File: LICENSE.txt
Classifier: Development Status :: 4 - Beta
Classifier: License :: OSI Approved :: MIT License
Classifier: Operating System :: Microsoft :: Windows :: Windows 10
Classifier: Programming Language :: Python
Classifier: Programming Language :: Python :: 3.10
Classifier: Programming Language :: Python :: 3.11
Classifier: Programming Language :: Python :: 3.12
Classifier: Programming Language :: Python :: Implementation :: CPython
Classifier: Programming Language :: Python :: Implementation :: PyPy
Classifier: Topic :: Scientific/Engineering :: GIS
Requires-Python: >=3.10
Requires-Dist: duckdb
Requires-Dist: geopandas<2,>=1.0.1
Requires-Dist: ipywidgets
Requires-Dist: osmnx<3,>=2.0.2
Requires-Dist: pyarrow<=20.0.0
Requires-Dist: pyproj<4,>=3.7.1
Requires-Dist: sentence-transformers<=4.1.0
Requires-Dist: shapely<3,>=2.0.7
Requires-Dist: typing-extensions
